pyluaredis/__init__.py
pyluaredis/client.py
pyluaredis/data_type_converter.py
pyluaredis/lua_scripts/append_value_to_array.lua
pyluaredis/lua_scripts/delete_or_unlink_with_returning.lua
pyluaredis/lua_scripts/drop_keys_ttl.lua
pyluaredis/lua_scripts/get_helper.lua
pyluaredis/lua_scripts/r_len.lua
pyluaredis/lua_scripts/r_mass_delete_or_unlink.lua
pyluaredis/lua_scripts/r_pop.lua
pyluaredis/lua_scripts/remove_all_keys_local.lua
pyluaredis/lua_scripts/rename_key.lua
pyluaredis/lua_scripts/set_arrays_helper.lua
pyluaredis/lua_scripts/set_keys_ttl.lua
pyluaredis/lua_scripts/set_not_array_helper.lua
pyluaredis-1.0.9.dist-info/licenses/LICENSE
pyluaredis-1.0.9.dist-info/METADATA
pyluaredis-1.0.9.dist-info/WHEEL
pyluaredis-1.0.9.dist-info/top_level.txt
pyluaredis-1.0.9.dist-info/RECORD
