Metadata-Version: 2.4
Name: pyluaredis
Version: 1.0.9
Summary: Pluggable client for easy and intuitive work with the Redis database in Python projects
License: MIT
Project-URL: Repository, https://github.com/MothScientist/pylua-redis-fusion
Project-URL: Issues, https://github.com/MothScientist/pylua-redis-fusion/issues
Keywords: package,redis
Requires-Python: >=3.11
License-File: LICENSE
Requires-Dist: redis==6.4.0
Dynamic: license-file
